Metadata-Version: 1.1
Name: slate
Version: 0.2.3
Summary: Extract text from PDF documents easily.
Home-page: http://pypi.python.org/pypi/slate
Author: Tim McNamara
Author-email: paperless@timmcnamara.co.nz
License: GPL v3 or later
Keywords: pdf,text,text-extraction
Platform: UNKNOWN
Classifier: Development Status :: 4 - Beta
Classifier: Intended Audience :: Developers
Classifier: License :: OSI Approved :: GNU General Public License (GPL)
Classifier: Programming Language :: Python
Classifier: Programming Language :: Python :: 2.6
Classifier: Topic :: Office/Business
Classifier: Topic :: Software Development :: Libraries :: Python Modules
Classifier: Topic :: Text Processing
Classifier: Topic :: Utilities
Requires: pdfminer
